LICENSE.txt
MANIFEST.in
README.rst
setup.cfg
setup.py
sqla_declarative/__init__.py
sqla_declarative/declarative.py
sqla_declarative.egg-info/PKG-INFO
sqla_declarative.egg-info/SOURCES.txt
sqla_declarative.egg-info/dependency_links.txt
sqla_declarative.egg-info/entry_points.txt
sqla_declarative.egg-info/not-zip-safe
sqla_declarative.egg-info/requires.txt
sqla_declarative.egg-info/top_level.txt