Metadata-Version: 1.1
Name: sqla-declarative
Version: 0.2
Summary: Extended SQLAlchemy declarative_base class
Home-page: https://github.com/LeResKP/sqla_declarative
Author: Aurélien Matouillot
Author-email: a.matouillot@gmail.com
License: MIT
Platform: UNKNOWN
Classifier: Topic :: Software Development :: Libraries :: Python Modules
Classifier: Intended Audience :: Developers
Classifier: Operating System :: OS Independent
Classifier: Programming Language :: Python
Classifier: Programming Language :: Python :: 2.6
Classifier: Programming Language :: Python :: 2.7
Classifier: Programming Language :: SQL
Classifier: Topic :: Database
Classifier: Topic :: Database :: Front-Ends
